litopys/__init__.py
litopys/main.py
litopys-0.0.1.dist-info/licenses/LICENSE.md
litopys-0.0.1.dist-info/METADATA
litopys-0.0.1.dist-info/WHEEL
litopys-0.0.1.dist-info/entry_points.txt
litopys-0.0.1.dist-info/top_level.txt
litopys-0.0.1.dist-info/RECORD
