Metadata-Version: 2.4
Name: litopys
Version: 0.0.1
Summary: Litopys - AI changelog generator
Author-email: Anton Bakhurynskyi <antoncodes@outlook.com>
License: Copyright (c) 2025 Anton Bakhurynskyi
Project-URL: Homepage, https://litopys.ai
Classifier: Programming Language :: Python :: 3
Classifier: Operating System :: OS Independent
Classifier: Development Status :: 3 - Alpha
Requires-Python: >=3.8
License-File: LICENSE.md
Dynamic: license-file
